LICENSE
MANIFEST.in
README.rst
setup.py
deiman/__init__.py
deiman/deiman.py
deiman.egg-info/PKG-INFO
deiman.egg-info/SOURCES.txt
deiman.egg-info/dependency_links.txt
deiman.egg-info/top_level.txt
deiman.egg-info/zip-safe