Metadata-Version: 1.1
Name: deiman
Version: 0.1.5
Summary: Deiman is a Python utility class for daemonizing a process. It provides start and stop methods, as well as a method for retrieving running status information. Linux/Unix-only.
Home-page: http://syslog.tv/deiman
Author: Kura
Author-email: kura@kura.io
License: (The MIT License)
